emrcalc/__init__.py
emrcalc/emrcalc_main.py
emrcalc/emrcalc_state.py
emrcalc/emrcalc_tk.py
emrcalc/emrcalc_utilities.py
emrcalc-1.4.0.dist-info/LICENSE
emrcalc-1.4.0.dist-info/METADATA
emrcalc-1.4.0.dist-info/WHEEL
emrcalc-1.4.0.dist-info/entry_points.txt
emrcalc-1.4.0.dist-info/top_level.txt
emrcalc-1.4.0.dist-info/RECORD
