Metadata-Version: 2.1
Name: emrcalc
Version: 1.4.0
Summary: Electromagnetic Radiation Calculator
Home-page: https://github.com/texadactyl/emrcalc
Author: Richard Elkins
Author-email: richard.elkins@gmail.com
License: GNU General Public License Version 3
Keywords: astronomy chemistry physics
Classifier: Development Status :: 4 - Beta
Classifier: Intended Audience :: Science/Research
Classifier: Programming Language :: Python :: 3
Classifier: Topic :: Scientific/Engineering
License-File: LICENSE
Requires-Dist: numpy
Requires-Dist: scipy
